{
    "data": [
        {
            "bank_url": "https://bincheck.io/es/cr/ath-costa-rica,-s.a.",
            "bank_name": "ATH COSTA RICA, S.A.",
            "country_name": "COSTA RICA",
            "country_img": "https://bincheck.io/assets/flags/svg/cr.svg",
            "country_url": "https://bincheck.io/es/cr"
        },
        {
            "bank_url": "https://bincheck.io/es/cr/aval-card-(costa-rica),-s.a.",
            "bank_name": "AVAL CARD (COSTA RICA), S.A.",
            "country_name": "COSTA RICA",
            "country_img": "https://bincheck.io/assets/flags/svg/cr.svg",
            "country_url": "https://bincheck.io/es/cr"
        },
        {
            "bank_url": "https://bincheck.io/es/cr/bac-international-bank",
            "bank_name": "BAC INTERNATIONAL BANK",
            "country_name": "COSTA RICA",
            "country_img": "https://bincheck.io/assets/flags/svg/cr.svg",
            "country_url": "https://bincheck.io/es/cr"
        },
        {
            "bank_url": "https://bincheck.io/es/cr/bac-san-jose",
            "bank_name": "BAC SAN JOSE",
            "country_name": "COSTA RICA",
            "country_img": "https://bincheck.io/assets/flags/svg/cr.svg",
            "country_url": "https://bincheck.io/es/cr"
        },
        {
            "bank_url": "https://bincheck.io/es/cr/banca-promerica,-s.a.",
            "bank_name": "BANCA PROMERICA, S.A.",
            "country_name": "COSTA RICA",
            "country_img": "https://bincheck.io/assets/flags/svg/cr.svg",
            "country_url": "https://bincheck.io/es/cr"
        },
        {
            "bank_url": "https://bincheck.io/es/cr/banco-bac-san-jose,-s.a.",
            "bank_name": "BANCO BAC SAN JOSE, S.A.",
            "country_name": "COSTA RICA",
            "country_img": "https://bincheck.io/assets/flags/svg/cr.svg",
            "country_url": "https://bincheck.io/es/cr"
        },
        {
            "bank_url": "https://bincheck.io/es/cr/banco-banex,-s.a.",
            "bank_name": "BANCO BANEX, S.A.",
            "country_name": "COSTA RICA",
            "country_img": "https://bincheck.io/assets/flags/svg/cr.svg",
            "country_url": "https://bincheck.io/es/cr"
        },
        {
            "bank_url": "https://bincheck.io/es/cr/banco-cathay-de-costa-rica,-s.a.",
            "bank_name": "BANCO CATHAY DE COSTA RICA, S.A.",
            "country_name": "COSTA RICA",
            "country_img": "https://bincheck.io/assets/flags/svg/cr.svg",
            "country_url": "https://bincheck.io/es/cr"
        },
        {
            "bank_url": "https://bincheck.io/es/cr/banco-citibank-de-costa-rica,-s.a.",
            "bank_name": "BANCO CITIBANK DE COSTA RICA, S.A.",
            "country_name": "COSTA RICA",
            "country_img": "https://bincheck.io/assets/flags/svg/cr.svg",
            "country_url": "https://bincheck.io/es/cr"
        },
        {
            "bank_url": "https://bincheck.io/es/cr/banco-credito-agricola-de-cartago",
            "bank_name": "BANCO CREDITO AGRICOLA DE CARTAGO",
            "country_name": "COSTA RICA",
            "country_img": "https://bincheck.io/assets/flags/svg/cr.svg",
            "country_url": "https://bincheck.io/es/cr"
        },
        {
            "bank_url": "https://bincheck.io/es/cr/banco-cuscatlan-de-costa-rica,-s.a.",
            "bank_name": "BANCO CUSCATLAN DE COSTA RICA, S.A.",
            "country_name": "COSTA RICA",
            "country_img": "https://bincheck.io/assets/flags/svg/cr.svg",
            "country_url": "https://bincheck.io/es/cr"
        },
        {
            "bank_url": "https://bincheck.io/es/cr/banco-davivienda-(costa-rica),-s.a.",
            "bank_name": "BANCO DAVIVIENDA (COSTA RICA), S.A.",
            "country_name": "COSTA RICA",
            "country_img": "https://bincheck.io/assets/flags/svg/cr.svg",
            "country_url": "https://bincheck.io/es/cr"
        },
        {
            "bank_url": "https://bincheck.io/es/cr/banco-davivienda-costa-rica-s.a.",
            "bank_name": "BANCO DAVIVIENDA COSTA RICA S.A.",
            "country_name": "COSTA RICA",
            "country_img": "https://bincheck.io/assets/flags/svg/cr.svg",
            "country_url": "https://bincheck.io/es/cr"
        },
        {
            "bank_url": "https://bincheck.io/es/cr/banco-de-costa-rica",
            "bank_name": "BANCO DE COSTA RICA",
            "country_name": "COSTA RICA",
            "country_img": "https://bincheck.io/assets/flags/svg/cr.svg",
            "country_url": "https://bincheck.io/es/cr"
        },
        {
            "bank_url": "https://bincheck.io/es/cr/banco-de-soluciones-bansol-de-costa-rica,-s.a.",
            "bank_name": "BANCO DE SOLUCIONES BANSOL DE COSTA RICA, S.A.",
            "country_name": "COSTA RICA",
            "country_img": "https://bincheck.io/assets/flags/svg/cr.svg",
            "country_url": "https://bincheck.io/es/cr"
        },
        {
            "bank_url": "https://bincheck.io/es/cr/banco-del-istmo-(costa-rica),-s.a.",
            "bank_name": "BANCO DEL ISTMO (COSTA RICA), S.A.",
            "country_name": "COSTA RICA",
            "country_img": "https://bincheck.io/assets/flags/svg/cr.svg",
            "country_url": "https://bincheck.io/es/cr"
        },
        {
            "bank_url": "https://bincheck.io/es/cr/banco-elca,-s.a.",
            "bank_name": "BANCO ELCA, S.A.",
            "country_name": "COSTA RICA",
            "country_img": "https://bincheck.io/assets/flags/svg/cr.svg",
            "country_url": "https://bincheck.io/es/cr"
        },
        {
            "bank_url": "https://bincheck.io/es/cr/banco-general-(costa-rica),-s.a.",
            "bank_name": "BANCO GENERAL (COSTA RICA), S.A.",
            "country_name": "COSTA RICA",
            "country_img": "https://bincheck.io/assets/flags/svg/cr.svg",
            "country_url": "https://bincheck.io/es/cr"
        },
        {
            "bank_url": "https://bincheck.io/es/cr/banco-hsbc-(costa-rica),-s.a.",
            "bank_name": "BANCO HSBC (COSTA RICA), S.A.",
            "country_name": "COSTA RICA",
            "country_img": "https://bincheck.io/assets/flags/svg/cr.svg",
            "country_url": "https://bincheck.io/es/cr"
        },
        {
            "bank_url": "https://bincheck.io/es/cr/banco-improsa,-s.a.",
            "bank_name": "BANCO IMPROSA, S.A.",
            "country_name": "COSTA RICA",
            "country_img": "https://bincheck.io/assets/flags/svg/cr.svg",
            "country_url": "https://bincheck.io/es/cr"
        },
        {
            "bank_url": "https://bincheck.io/es/cr/banco-interfin,-s.a.",
            "bank_name": "BANCO INTERFIN, S.A.",
            "country_name": "COSTA RICA",
            "country_img": "https://bincheck.io/assets/flags/svg/cr.svg",
            "country_url": "https://bincheck.io/es/cr"
        },
        {
            "bank_url": "https://bincheck.io/es/cr/banco-lafise,-s.a.",
            "bank_name": "BANCO LAFISE, S.A.",
            "country_name": "COSTA RICA",
            "country_img": "https://bincheck.io/assets/flags/svg/cr.svg",
            "country_url": "https://bincheck.io/es/cr"
        },
        {
            "bank_url": "https://bincheck.io/es/cr/banco-nacional-de-costa-rica",
            "bank_name": "BANCO NACIONAL DE COSTA RICA",
            "country_name": "COSTA RICA",
            "country_img": "https://bincheck.io/assets/flags/svg/cr.svg",
            "country_url": "https://bincheck.io/es/cr"
        },
        {
            "bank_url": "https://bincheck.io/es/cr/banco-popular-y-de-desarrollo-comunal",
            "bank_name": "BANCO POPULAR Y DE DESARROLLO COMUNAL",
            "country_name": "COSTA RICA",
            "country_img": "https://bincheck.io/assets/flags/svg/cr.svg",
            "country_url": "https://bincheck.io/es/cr"
        },
        {
            "bank_url": "https://bincheck.io/es/cr/banco-promerica-de-costa-rica-s.a.",
            "bank_name": "BANCO PROMERICA DE COSTA RICA S.A.",
            "country_name": "COSTA RICA",
            "country_img": "https://bincheck.io/assets/flags/svg/cr.svg",
            "country_url": "https://bincheck.io/es/cr"
        },
        {
            "bank_url": "https://bincheck.io/es/cr/banco-promerica-de-costa-rica-sa",
            "bank_name": "BANCO PROMERICA DE COSTA RICA SA",
            "country_name": "COSTA RICA",
            "country_img": "https://bincheck.io/assets/flags/svg/cr.svg",
            "country_url": "https://bincheck.io/es/cr"
        },
        {
            "bank_url": "https://bincheck.io/es/cr/banco-promerica-de-costa-rica,-s.a.",
            "bank_name": "BANCO PROMERICA DE COSTA RICA, S.A.",
            "country_name": "COSTA RICA",
            "country_img": "https://bincheck.io/assets/flags/svg/cr.svg",
            "country_url": "https://bincheck.io/es/cr"
        },
        {
            "bank_url": "https://bincheck.io/es/cr/banco-uno,-s.a.",
            "bank_name": "BANCO UNO, S.A.",
            "country_name": "COSTA RICA",
            "country_img": "https://bincheck.io/assets/flags/svg/cr.svg",
            "country_url": "https://bincheck.io/es/cr"
        },
        {
            "bank_url": "https://bincheck.io/es/cr/bicsacard,-s.a.",
            "bank_name": "BICSACARD, S.A.",
            "country_name": "COSTA RICA",
            "country_img": "https://bincheck.io/assets/flags/svg/cr.svg",
            "country_url": "https://bincheck.io/es/cr"
        },
        {
            "bank_url": "https://bincheck.io/es/cr/citibank-international",
            "bank_name": "CITIBANK INTERNATIONAL",
            "country_name": "COSTA RICA",
            "country_img": "https://bincheck.io/assets/flags/svg/cr.svg",
            "country_url": "https://bincheck.io/es/cr"
        },
        {
            "bank_url": "https://bincheck.io/es/cr/cititarjetas-de-costa-rica,-s.a.",
            "bank_name": "CITITARJETAS DE COSTA RICA, S.A.",
            "country_name": "COSTA RICA",
            "country_img": "https://bincheck.io/assets/flags/svg/cr.svg",
            "country_url": "https://bincheck.io/es/cr"
        },
        {
            "bank_url": "https://bincheck.io/es/cr/cooperativa-nacional-de-educad",
            "bank_name": "COOPERATIVA NACIONAL DE EDUCAD",
            "country_name": "COSTA RICA",
            "country_img": "https://bincheck.io/assets/flags/svg/cr.svg",
            "country_url": "https://bincheck.io/es/cr"
        },
        {
            "bank_url": "https://bincheck.io/es/cr/cooperativa-nacional-de-educadores",
            "bank_name": "COOPERATIVA NACIONAL DE EDUCADORES",
            "country_name": "COSTA RICA",
            "country_img": "https://bincheck.io/assets/flags/svg/cr.svg",
            "country_url": "https://bincheck.io/es/cr"
        },
        {
            "bank_url": "https://bincheck.io/es/cr/cooperativa-nacional-de-educadores-r.l",
            "bank_name": "COOPERATIVA NACIONAL DE EDUCADORES R.L",
            "country_name": "COSTA RICA",
            "country_img": "https://bincheck.io/assets/flags/svg/cr.svg",
            "country_url": "https://bincheck.io/es/cr"
        },
        {
            "bank_url": "https://bincheck.io/es/cr/cooperativa-nacional-de-educadores-r.l.-(coopenae-r.l.)",
            "bank_name": "COOPERATIVA NACIONAL DE EDUCADORES R.L. (COOPENAE R.L.)",
            "country_name": "COSTA RICA",
            "country_img": "https://bincheck.io/assets/flags/svg/cr.svg",
            "country_url": "https://bincheck.io/es/cr"
        },
        {
            "bank_url": "https://bincheck.io/es/cr/cooperativa-nacional-de-educadores,-r.l.(coopenae-rl)",
            "bank_name": "COOPERATIVA NACIONAL DE EDUCADORES, R.L.(COOPENAE RL)",
            "country_name": "COSTA RICA",
            "country_img": "https://bincheck.io/assets/flags/svg/cr.svg",
            "country_url": "https://bincheck.io/es/cr"
        },
        {
            "bank_url": "https://bincheck.io/es/cr/credix-internacional,-s.a.",
            "bank_name": "CREDIX INTERNACIONAL, S.A.",
            "country_name": "COSTA RICA",
            "country_img": "https://bincheck.io/assets/flags/svg/cr.svg",
            "country_url": "https://bincheck.io/es/cr"
        },
        {
            "bank_url": "https://bincheck.io/es/cr/credomatic-de-costa-rica",
            "bank_name": "CREDOMATIC DE COSTA RICA",
            "country_name": "COSTA RICA",
            "country_img": "https://bincheck.io/assets/flags/svg/cr.svg",
            "country_url": "https://bincheck.io/es/cr"
        },
        {
            "bank_url": "https://bincheck.io/es/cr/credomatic-international",
            "bank_name": "CREDOMATIC INTERNATIONAL",
            "country_name": "COSTA RICA",
            "country_img": "https://bincheck.io/assets/flags/svg/cr.svg",
            "country_url": "https://bincheck.io/es/cr"
        },
        {
            "bank_url": "https://bincheck.io/es/cr/credomatic-international,-s.a.",
            "bank_name": "CREDOMATIC INTERNATIONAL, S.A.",
            "country_name": "COSTA RICA",
            "country_img": "https://bincheck.io/assets/flags/svg/cr.svg",
            "country_url": "https://bincheck.io/es/cr"
        },
        {
            "bank_url": "https://bincheck.io/es/cr/crest,-s.a.",
            "bank_name": "CREST, S.A.",
            "country_name": "COSTA RICA",
            "country_img": "https://bincheck.io/assets/flags/svg/cr.svg",
            "country_url": "https://bincheck.io/es/cr"
        },
        {
            "bank_url": "https://bincheck.io/es/cr/emporiki-bank",
            "bank_name": "EMPORIKI BANK",
            "country_name": "COSTA RICA",
            "country_img": "https://bincheck.io/assets/flags/svg/cr.svg",
            "country_url": "https://bincheck.io/es/cr"
        },
        {
            "bank_url": "https://bincheck.io/es/cr/evertec-centroamerica,-s.a.",
            "bank_name": "EVERTEC CENTROAMERICA, S.A.",
            "country_name": "COSTA RICA",
            "country_img": "https://bincheck.io/assets/flags/svg/cr.svg",
            "country_url": "https://bincheck.io/es/cr"
        },
        {
            "bank_url": "https://bincheck.io/es/cr/grupo-financiero-bns-de-costa-rica-s.a.",
            "bank_name": "GRUPO FINANCIERO BNS DE COSTA RICA S.A.",
            "country_name": "COSTA RICA",
            "country_img": "https://bincheck.io/assets/flags/svg/cr.svg",
            "country_url": "https://bincheck.io/es/cr"
        },
        {
            "bank_url": "https://bincheck.io/es/cr/innovacion-en-medios-de-pago-e",
            "bank_name": "INNOVACION EN MEDIOS DE PAGO E",
            "country_name": "COSTA RICA",
            "country_img": "https://bincheck.io/assets/flags/svg/cr.svg",
            "country_url": "https://bincheck.io/es/cr"
        },
        {
            "bank_url": "https://bincheck.io/es/cr/innovacion-en-medios-de-pago-electronicos-s.a.(impesa)",
            "bank_name": "INNOVACION EN MEDIOS DE PAGO ELECTRONICOS S.A.(IMPESA)",
            "country_name": "COSTA RICA",
            "country_img": "https://bincheck.io/assets/flags/svg/cr.svg",
            "country_url": "https://bincheck.io/es/cr"
        },
        {
            "bank_url": "https://bincheck.io/es/cr/inversiones-fedeban,-s.a.",
            "bank_name": "INVERSIONES FEDEBAN, S.A.",
            "country_name": "COSTA RICA",
            "country_img": "https://bincheck.io/assets/flags/svg/cr.svg",
            "country_url": "https://bincheck.io/es/cr"
        },
        {
            "bank_url": "https://bincheck.io/es/cr/inversiones-itsmicas-bancrecen,-s.a.",
            "bank_name": "INVERSIONES ITSMICAS BANCRECEN, S.A.",
            "country_name": "COSTA RICA",
            "country_img": "https://bincheck.io/assets/flags/svg/cr.svg",
            "country_url": "https://bincheck.io/es/cr"
        },
        {
            "bank_url": "https://bincheck.io/es/cr/maestro-international",
            "bank_name": "MAESTRO INTERNATIONAL",
            "country_name": "COSTA RICA",
            "country_img": "https://bincheck.io/assets/flags/svg/cr.svg",
            "country_url": "https://bincheck.io/es/cr"
        },
        {
            "bank_url": "https://bincheck.io/es/cr/prival-bank-costa-rica--s.a.",
            "bank_name": "PRIVAL BANK COSTA RICA S.A.",
            "country_name": "COSTA RICA",
            "country_img": "https://bincheck.io/assets/flags/svg/cr.svg",
            "country_url": "https://bincheck.io/es/cr"
        },
        {
            "bank_url": "https://bincheck.io/es/cr/procard-de-costa-rica,-s.a.",
            "bank_name": "PROCARD DE COSTA RICA, S.A.",
            "country_name": "COSTA RICA",
            "country_img": "https://bincheck.io/assets/flags/svg/cr.svg",
            "country_url": "https://bincheck.io/es/cr"
        },
        {
            "bank_url": "https://bincheck.io/es/cr/prosix,-s.a.",
            "bank_name": "PROSIX, S.A.",
            "country_name": "COSTA RICA",
            "country_img": "https://bincheck.io/assets/flags/svg/cr.svg",
            "country_url": "https://bincheck.io/es/cr"
        },
        {
            "bank_url": "https://bincheck.io/es/cr/scotiabank-de-costa-rica,-s.a.",
            "bank_name": "SCOTIABANK DE COSTA RICA, S.A.",
            "country_name": "COSTA RICA",
            "country_img": "https://bincheck.io/assets/flags/svg/cr.svg",
            "country_url": "https://bincheck.io/es/cr"
        },
        {
            "bank_url": "https://bincheck.io/es/cr/scotiabank-el-salvador,-s.a.",
            "bank_name": "SCOTIABANK EL SALVADOR, S.A.",
            "country_name": "COSTA RICA",
            "country_img": "https://bincheck.io/assets/flags/svg/cr.svg",
            "country_url": "https://bincheck.io/es/cr"
        },
        {
            "bank_url": "https://bincheck.io/es/cr/tarjetas-bct,-s.a.",
            "bank_name": "TARJETAS BCT, S.A.",
            "country_name": "COSTA RICA",
            "country_img": "https://bincheck.io/assets/flags/svg/cr.svg",
            "country_url": "https://bincheck.io/es/cr"
        },
        {
            "bank_url": "https://bincheck.io/es/cr/tarjetas-bfa,-s.a.",
            "bank_name": "TARJETAS BFA, S.A.",
            "country_name": "COSTA RICA",
            "country_img": "https://bincheck.io/assets/flags/svg/cr.svg",
            "country_url": "https://bincheck.io/es/cr"
        },
        {
            "bank_url": "https://bincheck.io/es/cr/tecnicard,-inc.",
            "bank_name": "TECNICARD, INC.",
            "country_name": "COSTA RICA",
            "country_img": "https://bincheck.io/assets/flags/svg/cr.svg",
            "country_url": "https://bincheck.io/es/cr"
        },
        {
            "bank_url": "https://bincheck.io/es/cr/vales-intercontinentales-s.a.",
            "bank_name": "VALES INTERCONTINENTALES S.A.",
            "country_name": "COSTA RICA",
            "country_img": "https://bincheck.io/assets/flags/svg/cr.svg",
            "country_url": "https://bincheck.io/es/cr"
        },
        {
            "bank_url": "https://bincheck.io/es/cr/vales-intercontinentales,-s.a.",
            "bank_name": "VALES INTERCONTINENTALES, S.A.",
            "country_name": "COSTA RICA",
            "country_img": "https://bincheck.io/assets/flags/svg/cr.svg",
            "country_url": "https://bincheck.io/es/cr"
        },
        {
            "bank_url": "https://bincheck.io/es/cr/visa-argentina,-s.a.",
            "bank_name": "VISA ARGENTINA, S.A.",
            "country_name": "COSTA RICA",
            "country_img": "https://bincheck.io/assets/flags/svg/cr.svg",
            "country_url": "https://bincheck.io/es/cr"
        }
    ]
}