{
    "data": [
        {
            "bin_num": "512557",
            "bin_mark": "MASTERCARD",
            "bin_type": "CREDIT",
            "bin_level": "GOLD",
            "bank_name": "JOINT STOCK BANK DIAMANT (DIAMANTBANK)",
            "country_name": "UKRAINE",
            "country_img": "https://bincheck.io/assets/flags/svg/ua.svg",
            "country_url": "https://bincheck.io/es/ua",
            "bank_url": "https://bincheck.io/es/ua/joint-stock-bank-diamant-(diamantbank)"
        },
        {
            "bin_num": "512572",
            "bin_mark": "MASTERCARD",
            "bin_type": "CREDIT",
            "bin_level": "STANDARD",
            "bank_name": "JOINT STOCK BANK DIAMANT (DIAMANTBANK)",
            "country_name": "UKRAINE",
            "country_img": "https://bincheck.io/assets/flags/svg/ua.svg",
            "country_url": "https://bincheck.io/es/ua",
            "bank_url": "https://bincheck.io/es/ua/joint-stock-bank-diamant-(diamantbank)"
        },
        {
            "bin_num": "516760",
            "bin_mark": "MASTERCARD",
            "bin_type": "DEBIT",
            "bin_level": "STANDARD",
            "bank_name": "JOINT STOCK BANK DIAMANT (DIAMANTBANK)",
            "country_name": "UKRAINE",
            "country_img": "https://bincheck.io/assets/flags/svg/ua.svg",
            "country_url": "https://bincheck.io/es/ua",
            "bank_url": "https://bincheck.io/es/ua/joint-stock-bank-diamant-(diamantbank)"
        },
        {
            "bin_num": "535252",
            "bin_mark": "MASTERCARD",
            "bin_type": "DEBIT",
            "bin_level": "GOLD",
            "bank_name": "JOINT STOCK BANK DIAMANT (DIAMANTBANK)",
            "country_name": "UKRAINE",
            "country_img": "https://bincheck.io/assets/flags/svg/ua.svg",
            "country_url": "https://bincheck.io/es/ua",
            "bank_url": "https://bincheck.io/es/ua/joint-stock-bank-diamant-(diamantbank)"
        },
        {
            "bin_num": "547755",
            "bin_mark": "MASTERCARD",
            "bin_type": "CREDIT",
            "bin_level": "BUSINESS",
            "bank_name": "JOINT STOCK BANK DIAMANT (DIAMANTBANK)",
            "country_name": "UKRAINE",
            "country_img": "https://bincheck.io/assets/flags/svg/ua.svg",
            "country_url": "https://bincheck.io/es/ua",
            "bank_url": "https://bincheck.io/es/ua/joint-stock-bank-diamant-(diamantbank)"
        },
        {
            "bin_num": "676678",
            "bin_mark": "MAESTRO",
            "bin_type": "DEBIT",
            "bin_level": "",
            "bank_name": "JOINT STOCK BANK DIAMANT (DIAMANTBANK)",
            "country_name": "UKRAINE",
            "country_img": "https://bincheck.io/assets/flags/svg/ua.svg",
            "country_url": "https://bincheck.io/es/ua",
            "bank_url": "https://bincheck.io/es/ua/joint-stock-bank-diamant-(diamantbank)"
        }
    ]
}