{
    "data": [
        {
            "bin_num": "403982",
            "bin_mark": "VISA",
            "bin_type": "DEBIT",
            "bin_level": "CLASSIC",
            "bank_name": "CREDIT UNION 1",
            "country_name": "UNITED STATES",
            "country_img": "https://bincheck.io/assets/flags/svg/us.svg",
            "country_url": "https://bincheck.io/es/us",
            "bank_url": "https://bincheck.io/es/us/credit-union-1"
        },
        {
            "bin_num": "412507",
            "bin_mark": "VISA",
            "bin_type": "DEBIT",
            "bin_level": "CLASSIC",
            "bank_name": "CREDIT UNION 1",
            "country_name": "UNITED STATES",
            "country_img": "https://bincheck.io/assets/flags/svg/us.svg",
            "country_url": "https://bincheck.io/es/us",
            "bank_url": "https://bincheck.io/es/us/credit-union-1"
        },
        {
            "bin_num": "420906",
            "bin_mark": "VISA",
            "bin_type": "CREDIT",
            "bin_level": "",
            "bank_name": "CREDIT UNION 1",
            "country_name": "UNITED STATES",
            "country_img": "https://bincheck.io/assets/flags/svg/us.svg",
            "country_url": "https://bincheck.io/es/us",
            "bank_url": "https://bincheck.io/es/us/credit-union-1"
        },
        {
            "bin_num": "423751",
            "bin_mark": "VISA",
            "bin_type": "CREDIT",
            "bin_level": "CLASSIC",
            "bank_name": "CREDIT UNION 1",
            "country_name": "UNITED STATES",
            "country_img": "https://bincheck.io/assets/flags/svg/us.svg",
            "country_url": "https://bincheck.io/es/us",
            "bank_url": "https://bincheck.io/es/us/credit-union-1"
        },
        {
            "bin_num": "426936",
            "bin_mark": "VISA",
            "bin_type": "DEBIT",
            "bin_level": "CLASSIC",
            "bank_name": "CREDIT UNION 1",
            "country_name": "UNITED STATES",
            "country_img": "https://bincheck.io/assets/flags/svg/us.svg",
            "country_url": "https://bincheck.io/es/us",
            "bank_url": "https://bincheck.io/es/us/credit-union-1"
        },
        {
            "bin_num": "430853",
            "bin_mark": "VISA",
            "bin_type": "CREDIT",
            "bin_level": "CLASSIC",
            "bank_name": "CREDIT UNION 1",
            "country_name": "UNITED STATES",
            "country_img": "https://bincheck.io/assets/flags/svg/us.svg",
            "country_url": "https://bincheck.io/es/us",
            "bank_url": "https://bincheck.io/es/us/credit-union-1"
        },
        {
            "bin_num": "433039",
            "bin_mark": "VISA",
            "bin_type": "DEBIT",
            "bin_level": "CLASSIC",
            "bank_name": "CREDIT UNION 1",
            "country_name": "UNITED STATES",
            "country_img": "https://bincheck.io/assets/flags/svg/us.svg",
            "country_url": "https://bincheck.io/es/us",
            "bank_url": "https://bincheck.io/es/us/credit-union-1"
        },
        {
            "bin_num": "434110",
            "bin_mark": "VISA",
            "bin_type": "CREDIT",
            "bin_level": "CLASSIC",
            "bank_name": "CREDIT UNION 1",
            "country_name": "UNITED STATES",
            "country_img": "https://bincheck.io/assets/flags/svg/us.svg",
            "country_url": "https://bincheck.io/es/us",
            "bank_url": "https://bincheck.io/es/us/credit-union-1"
        },
        {
            "bin_num": "442698",
            "bin_mark": "VISA",
            "bin_type": "CREDIT",
            "bin_level": "CLASSIC",
            "bank_name": "CREDIT UNION 1",
            "country_name": "UNITED STATES",
            "country_img": "https://bincheck.io/assets/flags/svg/us.svg",
            "country_url": "https://bincheck.io/es/us",
            "bank_url": "https://bincheck.io/es/us/credit-union-1"
        },
        {
            "bin_num": "442699",
            "bin_mark": "VISA",
            "bin_type": "CREDIT",
            "bin_level": "GOLD",
            "bank_name": "CREDIT UNION 1",
            "country_name": "UNITED STATES",
            "country_img": "https://bincheck.io/assets/flags/svg/us.svg",
            "country_url": "https://bincheck.io/es/us",
            "bank_url": "https://bincheck.io/es/us/credit-union-1"
        },
        {
            "bin_num": "444797",
            "bin_mark": "VISA",
            "bin_type": "DEBIT",
            "bin_level": "CLASSIC",
            "bank_name": "CREDIT UNION 1",
            "country_name": "UNITED STATES",
            "country_img": "https://bincheck.io/assets/flags/svg/us.svg",
            "country_url": "https://bincheck.io/es/us",
            "bank_url": "https://bincheck.io/es/us/credit-union-1"
        },
        {
            "bin_num": "447609",
            "bin_mark": "VISA",
            "bin_type": "DEBIT",
            "bin_level": "CLASSIC",
            "bank_name": "CREDIT UNION 1",
            "country_name": "UNITED STATES",
            "country_img": "https://bincheck.io/assets/flags/svg/us.svg",
            "country_url": "https://bincheck.io/es/us",
            "bank_url": "https://bincheck.io/es/us/credit-union-1"
        },
        {
            "bin_num": "447813",
            "bin_mark": "VISA",
            "bin_type": "CREDIT",
            "bin_level": "CLASSIC",
            "bank_name": "CREDIT UNION 1",
            "country_name": "UNITED STATES",
            "country_img": "https://bincheck.io/assets/flags/svg/us.svg",
            "country_url": "https://bincheck.io/es/us",
            "bank_url": "https://bincheck.io/es/us/credit-union-1"
        },
        {
            "bin_num": "447814",
            "bin_mark": "VISA",
            "bin_type": "CREDIT",
            "bin_level": "CLASSIC",
            "bank_name": "CREDIT UNION 1",
            "country_name": "UNITED STATES",
            "country_img": "https://bincheck.io/assets/flags/svg/us.svg",
            "country_url": "https://bincheck.io/es/us",
            "bank_url": "https://bincheck.io/es/us/credit-union-1"
        },
        {
            "bin_num": "447893",
            "bin_mark": "VISA",
            "bin_type": "CREDIT",
            "bin_level": "CLASSIC",
            "bank_name": "CREDIT UNION 1",
            "country_name": "UNITED STATES",
            "country_img": "https://bincheck.io/assets/flags/svg/us.svg",
            "country_url": "https://bincheck.io/es/us",
            "bank_url": "https://bincheck.io/es/us/credit-union-1"
        },
        {
            "bin_num": "449812",
            "bin_mark": "VISA",
            "bin_type": "CREDIT",
            "bin_level": "CLASSIC",
            "bank_name": "CREDIT UNION 1",
            "country_name": "UNITED STATES",
            "country_img": "https://bincheck.io/assets/flags/svg/us.svg",
            "country_url": "https://bincheck.io/es/us",
            "bank_url": "https://bincheck.io/es/us/credit-union-1"
        },
        {
            "bin_num": "460722",
            "bin_mark": "VISA",
            "bin_type": "DEBIT",
            "bin_level": "CLASSIC",
            "bank_name": "CREDIT UNION 1",
            "country_name": "UNITED STATES",
            "country_img": "https://bincheck.io/assets/flags/svg/us.svg",
            "country_url": "https://bincheck.io/es/us",
            "bank_url": "https://bincheck.io/es/us/credit-union-1"
        },
        {
            "bin_num": "460736",
            "bin_mark": "VISA",
            "bin_type": "DEBIT",
            "bin_level": "CLASSIC",
            "bank_name": "CREDIT UNION 1",
            "country_name": "UNITED STATES",
            "country_img": "https://bincheck.io/assets/flags/svg/us.svg",
            "country_url": "https://bincheck.io/es/us",
            "bank_url": "https://bincheck.io/es/us/credit-union-1"
        },
        {
            "bin_num": "475410",
            "bin_mark": "VISA",
            "bin_type": "DEBIT",
            "bin_level": "PREPAID",
            "bank_name": "CREDIT UNION 1",
            "country_name": "UNITED STATES",
            "country_img": "https://bincheck.io/assets/flags/svg/us.svg",
            "country_url": "https://bincheck.io/es/us",
            "bank_url": "https://bincheck.io/es/us/credit-union-1"
        },
        {
            "bin_num": "478946",
            "bin_mark": "VISA",
            "bin_type": "DEBIT",
            "bin_level": "CLASSIC",
            "bank_name": "CREDIT UNION 1",
            "country_name": "UNITED STATES",
            "country_img": "https://bincheck.io/assets/flags/svg/us.svg",
            "country_url": "https://bincheck.io/es/us",
            "bank_url": "https://bincheck.io/es/us/credit-union-1"
        },
        {
            "bin_num": "487293",
            "bin_mark": "VISA",
            "bin_type": "CREDIT",
            "bin_level": "CLASSIC",
            "bank_name": "CREDIT UNION 1",
            "country_name": "UNITED STATES",
            "country_img": "https://bincheck.io/assets/flags/svg/us.svg",
            "country_url": "https://bincheck.io/es/us",
            "bank_url": "https://bincheck.io/es/us/credit-union-1"
        },
        {
            "bin_num": "519264",
            "bin_mark": "MASTERCARD",
            "bin_type": "CREDIT",
            "bin_level": "STANDARD",
            "bank_name": "CREDIT UNION 1",
            "country_name": "UNITED STATES",
            "country_img": "https://bincheck.io/assets/flags/svg/us.svg",
            "country_url": "https://bincheck.io/es/us",
            "bank_url": "https://bincheck.io/es/us/credit-union-1"
        },
        {
            "bin_num": "519882",
            "bin_mark": "MASTERCARD",
            "bin_type": "DEBIT",
            "bin_level": "ENHANCED",
            "bank_name": "CREDIT UNION 1",
            "country_name": "UNITED STATES",
            "country_img": "https://bincheck.io/assets/flags/svg/us.svg",
            "country_url": "https://bincheck.io/es/us",
            "bank_url": "https://bincheck.io/es/us/credit-union-1"
        },
        {
            "bin_num": "523788",
            "bin_mark": "MASTERCARD",
            "bin_type": "CREDIT",
            "bin_level": "STANDARD",
            "bank_name": "CREDIT UNION 1",
            "country_name": "UNITED STATES",
            "country_img": "https://bincheck.io/assets/flags/svg/us.svg",
            "country_url": "https://bincheck.io/es/us",
            "bank_url": "https://bincheck.io/es/us/credit-union-1"
        },
        {
            "bin_num": "524932",
            "bin_mark": "MASTERCARD",
            "bin_type": "CREDIT",
            "bin_level": "PLATINUM",
            "bank_name": "CREDIT UNION 1",
            "country_name": "UNITED STATES",
            "country_img": "https://bincheck.io/assets/flags/svg/us.svg",
            "country_url": "https://bincheck.io/es/us",
            "bank_url": "https://bincheck.io/es/us/credit-union-1"
        },
        {
            "bin_num": "525722",
            "bin_mark": "MASTERCARD",
            "bin_type": "CREDIT",
            "bin_level": "GOLD",
            "bank_name": "CREDIT UNION 1",
            "country_name": "UNITED STATES",
            "country_img": "https://bincheck.io/assets/flags/svg/us.svg",
            "country_url": "https://bincheck.io/es/us",
            "bank_url": "https://bincheck.io/es/us/credit-union-1"
        },
        {
            "bin_num": "537982",
            "bin_mark": "MASTERCARD",
            "bin_type": "CREDIT",
            "bin_level": "PLATINUM",
            "bank_name": "CREDIT UNION 1",
            "country_name": "UNITED STATES",
            "country_img": "https://bincheck.io/assets/flags/svg/us.svg",
            "country_url": "https://bincheck.io/es/us",
            "bank_url": "https://bincheck.io/es/us/credit-union-1"
        }
    ]
}