{
    "data": [
        {
            "bin_num": "540992",
            "bin_mark": "MASTERCARD",
            "bin_type": "CREDIT",
            "bin_level": "GOLD",
            "bank_name": "FRANKLIN TEMPLETON BANK AND TRUST, F.S.B.",
            "country_name": "UNITED STATES",
            "country_img": "https://bincheck.io/assets/flags/svg/us.svg",
            "country_url": "https://bincheck.io/es/us",
            "bank_url": "https://bincheck.io/es/us/franklin-templeton-bank-and-trust,-f.s.b."
        }
    ]
}