{
    "data": [
        {
            "bin_num": "604476",
            "bin_mark": "MAESTRO",
            "bin_type": "CREDIT",
            "bin_level": "IKEA CARD",
            "bank_name": "IKEA CARD",
            "country_name": "CANADA",
            "country_img": "https://bincheck.io/assets/flags/svg/ca.svg",
            "country_url": "https://bincheck.io/es/ca",
            "bank_url": "https://bincheck.io/es/ca/ikea-card"
        },
        {
            "bin_num": "604477",
            "bin_mark": "MAESTRO",
            "bin_type": "CREDIT",
            "bin_level": "IKEA CARD",
            "bank_name": "IKEA CARD",
            "country_name": "CANADA",
            "country_img": "https://bincheck.io/assets/flags/svg/ca.svg",
            "country_url": "https://bincheck.io/es/ca",
            "bank_url": "https://bincheck.io/es/ca/ikea-card"
        },
        {
            "bin_num": "604478",
            "bin_mark": "MAESTRO",
            "bin_type": "CREDIT",
            "bin_level": "IKEA CARD",
            "bank_name": "IKEA CARD",
            "country_name": "CANADA",
            "country_img": "https://bincheck.io/assets/flags/svg/ca.svg",
            "country_url": "https://bincheck.io/es/ca",
            "bank_url": "https://bincheck.io/es/ca/ikea-card"
        },
        {
            "bin_num": "604479",
            "bin_mark": "MAESTRO",
            "bin_type": "CREDIT",
            "bin_level": "IKEA CARD",
            "bank_name": "IKEA CARD",
            "country_name": "CANADA",
            "country_img": "https://bincheck.io/assets/flags/svg/ca.svg",
            "country_url": "https://bincheck.io/es/ca",
            "bank_url": "https://bincheck.io/es/ca/ikea-card"
        },
        {
            "bin_num": "604480",
            "bin_mark": "MAESTRO",
            "bin_type": "CREDIT",
            "bin_level": "IKEA CARD",
            "bank_name": "IKEA CARD",
            "country_name": "CANADA",
            "country_img": "https://bincheck.io/assets/flags/svg/ca.svg",
            "country_url": "https://bincheck.io/es/ca",
            "bank_url": "https://bincheck.io/es/ca/ikea-card"
        },
        {
            "bin_num": "604481",
            "bin_mark": "MAESTRO",
            "bin_type": "CREDIT",
            "bin_level": "IKEA CARD",
            "bank_name": "IKEA CARD",
            "country_name": "CANADA",
            "country_img": "https://bincheck.io/assets/flags/svg/ca.svg",
            "country_url": "https://bincheck.io/es/ca",
            "bank_url": "https://bincheck.io/es/ca/ikea-card"
        },
        {
            "bin_num": "604483",
            "bin_mark": "MAESTRO",
            "bin_type": "CREDIT",
            "bin_level": "IKEA CARD",
            "bank_name": "IKEA CARD",
            "country_name": "CANADA",
            "country_img": "https://bincheck.io/assets/flags/svg/ca.svg",
            "country_url": "https://bincheck.io/es/ca",
            "bank_url": "https://bincheck.io/es/ca/ikea-card"
        },
        {
            "bin_num": "604484",
            "bin_mark": "MAESTRO",
            "bin_type": "DEBIT",
            "bin_level": "ELECTRON",
            "bank_name": "IKEA CARD",
            "country_name": "CANADA",
            "country_img": "https://bincheck.io/assets/flags/svg/ca.svg",
            "country_url": "https://bincheck.io/es/ca",
            "bank_url": "https://bincheck.io/es/ca/ikea-card"
        },
        {
            "bin_num": "604485",
            "bin_mark": "MAESTRO",
            "bin_type": "CREDIT",
            "bin_level": "IKEA CARD",
            "bank_name": "IKEA CARD",
            "country_name": "CANADA",
            "country_img": "https://bincheck.io/assets/flags/svg/ca.svg",
            "country_url": "https://bincheck.io/es/ca",
            "bank_url": "https://bincheck.io/es/ca/ikea-card"
        },
        {
            "bin_num": "604486",
            "bin_mark": "MAESTRO",
            "bin_type": "DEBIT",
            "bin_level": "ELECTRON",
            "bank_name": "IKEA CARD",
            "country_name": "CANADA",
            "country_img": "https://bincheck.io/assets/flags/svg/ca.svg",
            "country_url": "https://bincheck.io/es/ca",
            "bank_url": "https://bincheck.io/es/ca/ikea-card"
        },
        {
            "bin_num": "604487",
            "bin_mark": "MAESTRO",
            "bin_type": "CREDIT",
            "bin_level": "IKEA CARD",
            "bank_name": "IKEA CARD",
            "country_name": "CANADA",
            "country_img": "https://bincheck.io/assets/flags/svg/ca.svg",
            "country_url": "https://bincheck.io/es/ca",
            "bank_url": "https://bincheck.io/es/ca/ikea-card"
        },
        {
            "bin_num": "604488",
            "bin_mark": "MAESTRO",
            "bin_type": "CREDIT",
            "bin_level": "IKEA CARD",
            "bank_name": "IKEA CARD",
            "country_name": "CANADA",
            "country_img": "https://bincheck.io/assets/flags/svg/ca.svg",
            "country_url": "https://bincheck.io/es/ca",
            "bank_url": "https://bincheck.io/es/ca/ikea-card"
        },
        {
            "bin_num": "604489",
            "bin_mark": "MAESTRO",
            "bin_type": "DEBIT",
            "bin_level": "ELECTRON",
            "bank_name": "IKEA CARD",
            "country_name": "CANADA",
            "country_img": "https://bincheck.io/assets/flags/svg/ca.svg",
            "country_url": "https://bincheck.io/es/ca",
            "bank_url": "https://bincheck.io/es/ca/ikea-card"
        },
        {
            "bin_num": "604490",
            "bin_mark": "MAESTRO",
            "bin_type": "CREDIT",
            "bin_level": "IKEA CARD",
            "bank_name": "IKEA CARD",
            "country_name": "CANADA",
            "country_img": "https://bincheck.io/assets/flags/svg/ca.svg",
            "country_url": "https://bincheck.io/es/ca",
            "bank_url": "https://bincheck.io/es/ca/ikea-card"
        },
        {
            "bin_num": "604492",
            "bin_mark": "MAESTRO",
            "bin_type": "DEBIT",
            "bin_level": "ELECTRON",
            "bank_name": "IKEA CARD",
            "country_name": "CANADA",
            "country_img": "https://bincheck.io/assets/flags/svg/ca.svg",
            "country_url": "https://bincheck.io/es/ca",
            "bank_url": "https://bincheck.io/es/ca/ikea-card"
        },
        {
            "bin_num": "604496",
            "bin_mark": "MAESTRO",
            "bin_type": "CREDIT",
            "bin_level": "IKEA CARD",
            "bank_name": "IKEA CARD",
            "country_name": "CANADA",
            "country_img": "https://bincheck.io/assets/flags/svg/ca.svg",
            "country_url": "https://bincheck.io/es/ca",
            "bank_url": "https://bincheck.io/es/ca/ikea-card"
        }
    ]
}