{
    "data": [
        {
            "bin_num": "527277",
            "bin_mark": "MASTERCARD",
            "bin_type": "DEBIT",
            "bin_level": "STANDARD",
            "bank_name": "CAIRO AMMAN BANK PLC",
            "country_name": "JORDAN",
            "country_img": "https://bincheck.io/assets/flags/svg/jo.svg",
            "country_url": "https://bincheck.io/es/jo",
            "bank_url": "https://bincheck.io/es/jo/cairo-amman-bank-plc"
        },
        {
            "bin_num": "527281",
            "bin_mark": "MASTERCARD",
            "bin_type": "CREDIT",
            "bin_level": "TITANIUM",
            "bank_name": "CAIRO AMMAN BANK PLC",
            "country_name": "JORDAN",
            "country_img": "https://bincheck.io/assets/flags/svg/jo.svg",
            "country_url": "https://bincheck.io/es/jo",
            "bank_url": "https://bincheck.io/es/jo/cairo-amman-bank-plc"
        },
        {
            "bin_num": "534418",
            "bin_mark": "MASTERCARD",
            "bin_type": "DEBIT",
            "bin_level": "BUSINESS",
            "bank_name": "CAIRO AMMAN BANK PLC",
            "country_name": "JORDAN",
            "country_img": "https://bincheck.io/assets/flags/svg/jo.svg",
            "country_url": "https://bincheck.io/es/jo",
            "bank_url": "https://bincheck.io/es/jo/cairo-amman-bank-plc"
        },
        {
            "bin_num": "536290",
            "bin_mark": "MASTERCARD",
            "bin_type": "CREDIT",
            "bin_level": "WORLD",
            "bank_name": "CAIRO AMMAN BANK PLC",
            "country_name": "JORDAN",
            "country_img": "https://bincheck.io/assets/flags/svg/jo.svg",
            "country_url": "https://bincheck.io/es/jo",
            "bank_url": "https://bincheck.io/es/jo/cairo-amman-bank-plc"
        },
        {
            "bin_num": "536346",
            "bin_mark": "MASTERCARD",
            "bin_type": "DEBIT",
            "bin_level": "STANDARD",
            "bank_name": "CAIRO AMMAN BANK PLC",
            "country_name": "JORDAN",
            "country_img": "https://bincheck.io/assets/flags/svg/jo.svg",
            "country_url": "https://bincheck.io/es/jo",
            "bank_url": "https://bincheck.io/es/jo/cairo-amman-bank-plc"
        },
        {
            "bin_num": "538871",
            "bin_mark": "MASTERCARD",
            "bin_type": "DEBIT",
            "bin_level": "TITANIUM",
            "bank_name": "CAIRO AMMAN BANK PLC",
            "country_name": "JORDAN",
            "country_img": "https://bincheck.io/assets/flags/svg/jo.svg",
            "country_url": "https://bincheck.io/es/jo",
            "bank_url": "https://bincheck.io/es/jo/cairo-amman-bank-plc"
        },
        {
            "bin_num": "540498",
            "bin_mark": "MASTERCARD",
            "bin_type": "CREDIT",
            "bin_level": "STANDARD",
            "bank_name": "CAIRO AMMAN BANK PLC",
            "country_name": "JORDAN",
            "country_img": "https://bincheck.io/assets/flags/svg/jo.svg",
            "country_url": "https://bincheck.io/es/jo",
            "bank_url": "https://bincheck.io/es/jo/cairo-amman-bank-plc"
        },
        {
            "bin_num": "544378",
            "bin_mark": "MASTERCARD",
            "bin_type": "DEBIT",
            "bin_level": "PREPAID RELOADABLE",
            "bank_name": "CAIRO AMMAN BANK PLC",
            "country_name": "JORDAN",
            "country_img": "https://bincheck.io/assets/flags/svg/jo.svg",
            "country_url": "https://bincheck.io/es/jo",
            "bank_url": "https://bincheck.io/es/jo/cairo-amman-bank-plc"
        },
        {
            "bin_num": "550483",
            "bin_mark": "MASTERCARD",
            "bin_type": "DEBIT",
            "bin_level": "PREPAID RELOADABLE",
            "bank_name": "CAIRO AMMAN BANK PLC",
            "country_name": "JORDAN",
            "country_img": "https://bincheck.io/assets/flags/svg/jo.svg",
            "country_url": "https://bincheck.io/es/jo",
            "bank_url": "https://bincheck.io/es/jo/cairo-amman-bank-plc"
        },
        {
            "bin_num": "554682",
            "bin_mark": "",
            "bin_type": "DEBIT",
            "bin_level": "PREPAID RELOADABLE",
            "bank_name": "CAIRO AMMAN BANK PLC",
            "country_name": "JORDAN",
            "country_img": "https://bincheck.io/assets/flags/svg/jo.svg",
            "country_url": "https://bincheck.io/es/jo",
            "bank_url": "https://bincheck.io/es/jo/cairo-amman-bank-plc"
        },
        {
            "bin_num": "557063",
            "bin_mark": "MASTERCARD",
            "bin_type": "DEBIT",
            "bin_level": "PREPAID RELOADABLE",
            "bank_name": "CAIRO AMMAN BANK PLC",
            "country_name": "JORDAN",
            "country_img": "https://bincheck.io/assets/flags/svg/jo.svg",
            "country_url": "https://bincheck.io/es/jo",
            "bank_url": "https://bincheck.io/es/jo/cairo-amman-bank-plc"
        },
        {
            "bin_num": "559923",
            "bin_mark": "MASTERCARD",
            "bin_type": "DEBIT",
            "bin_level": "PREPAID RELOADABLE",
            "bank_name": "CAIRO AMMAN BANK PLC",
            "country_name": "JORDAN",
            "country_img": "https://bincheck.io/assets/flags/svg/jo.svg",
            "country_url": "https://bincheck.io/es/jo",
            "bank_url": "https://bincheck.io/es/jo/cairo-amman-bank-plc"
        },
        {
            "bin_num": "559938",
            "bin_mark": "MASTERCARD",
            "bin_type": "DEBIT",
            "bin_level": "PREPAID RELOADABLE",
            "bank_name": "CAIRO AMMAN BANK PLC",
            "country_name": "JORDAN",
            "country_img": "https://bincheck.io/assets/flags/svg/jo.svg",
            "country_url": "https://bincheck.io/es/jo",
            "bank_url": "https://bincheck.io/es/jo/cairo-amman-bank-plc"
        }
    ]
}