{
    "data": [
        {
            "bin_num": "429777",
            "bin_mark": "VISA",
            "bin_type": "CREDIT",
            "bin_level": "",
            "bank_name": "ABN AMRO BANK, N.V.",
            "country_name": "NETHERLANDS",
            "country_img": "https://bincheck.io/assets/flags/svg/nl.svg",
            "country_url": "https://bincheck.io/es/nl",
            "bank_url": "https://bincheck.io/es/nl/abn-amro-bank,-n.v."
        },
        {
            "bin_num": "430245",
            "bin_mark": "VISA",
            "bin_type": "CREDIT",
            "bin_level": "",
            "bank_name": "ABN AMRO BANK, N.V.",
            "country_name": "NETHERLANDS",
            "country_img": "https://bincheck.io/assets/flags/svg/nl.svg",
            "country_url": "https://bincheck.io/es/nl",
            "bank_url": "https://bincheck.io/es/nl/abn-amro-bank,-n.v."
        },
        {
            "bin_num": "430246",
            "bin_mark": "VISA",
            "bin_type": "CREDIT",
            "bin_level": "",
            "bank_name": "ABN AMRO BANK, N.V.",
            "country_name": "NETHERLANDS",
            "country_img": "https://bincheck.io/assets/flags/svg/nl.svg",
            "country_url": "https://bincheck.io/es/nl",
            "bank_url": "https://bincheck.io/es/nl/abn-amro-bank,-n.v."
        },
        {
            "bin_num": "430247",
            "bin_mark": "VISA",
            "bin_type": "CREDIT",
            "bin_level": "",
            "bank_name": "ABN AMRO BANK, N.V.",
            "country_name": "NETHERLANDS",
            "country_img": "https://bincheck.io/assets/flags/svg/nl.svg",
            "country_url": "https://bincheck.io/es/nl",
            "bank_url": "https://bincheck.io/es/nl/abn-amro-bank,-n.v."
        },
        {
            "bin_num": "430248",
            "bin_mark": "VISA",
            "bin_type": "CREDIT",
            "bin_level": "",
            "bank_name": "ABN AMRO BANK, N.V.",
            "country_name": "NETHERLANDS",
            "country_img": "https://bincheck.io/assets/flags/svg/nl.svg",
            "country_url": "https://bincheck.io/es/nl",
            "bank_url": "https://bincheck.io/es/nl/abn-amro-bank,-n.v."
        },
        {
            "bin_num": "430249",
            "bin_mark": "VISA",
            "bin_type": "CREDIT",
            "bin_level": "",
            "bank_name": "ABN AMRO BANK, N.V.",
            "country_name": "NETHERLANDS",
            "country_img": "https://bincheck.io/assets/flags/svg/nl.svg",
            "country_url": "https://bincheck.io/es/nl",
            "bank_url": "https://bincheck.io/es/nl/abn-amro-bank,-n.v."
        },
        {
            "bin_num": "430250",
            "bin_mark": "VISA",
            "bin_type": "CREDIT",
            "bin_level": "",
            "bank_name": "ABN AMRO BANK, N.V.",
            "country_name": "NETHERLANDS",
            "country_img": "https://bincheck.io/assets/flags/svg/nl.svg",
            "country_url": "https://bincheck.io/es/nl",
            "bank_url": "https://bincheck.io/es/nl/abn-amro-bank,-n.v."
        },
        {
            "bin_num": "448521",
            "bin_mark": "VISA",
            "bin_type": "CREDIT",
            "bin_level": "PURCHASING",
            "bank_name": "ABN AMRO BANK, N.V.",
            "country_name": "NETHERLANDS",
            "country_img": "https://bincheck.io/assets/flags/svg/nl.svg",
            "country_url": "https://bincheck.io/es/nl",
            "bank_url": "https://bincheck.io/es/nl/abn-amro-bank,-n.v."
        },
        {
            "bin_num": "472906",
            "bin_mark": "VISA",
            "bin_type": "DEBIT",
            "bin_level": "PREPAID",
            "bank_name": "ABN AMRO BANK, N.V.",
            "country_name": "NETHERLANDS",
            "country_img": "https://bincheck.io/assets/flags/svg/nl.svg",
            "country_url": "https://bincheck.io/es/nl",
            "bank_url": "https://bincheck.io/es/nl/abn-amro-bank,-n.v."
        },
        {
            "bin_num": "474131",
            "bin_mark": "VISA",
            "bin_type": "CREDIT",
            "bin_level": "CLASSIC",
            "bank_name": "ABN AMRO BANK, N.V.",
            "country_name": "NETHERLANDS",
            "country_img": "https://bincheck.io/assets/flags/svg/nl.svg",
            "country_url": "https://bincheck.io/es/nl",
            "bank_url": "https://bincheck.io/es/nl/abn-amro-bank,-n.v."
        },
        {
            "bin_num": "487531",
            "bin_mark": "VISA",
            "bin_type": "CREDIT",
            "bin_level": "",
            "bank_name": "ABN AMRO BANK, N.V.",
            "country_name": "NETHERLANDS",
            "country_img": "https://bincheck.io/assets/flags/svg/nl.svg",
            "country_url": "https://bincheck.io/es/nl",
            "bank_url": "https://bincheck.io/es/nl/abn-amro-bank,-n.v."
        }
    ]
}