{
    "data": [
        {
            "bin_num": "220095",
            "bin_mark": "NSPK",
            "bin_type": "DEBIT",
            "bin_level": "CLASSIC",
            "bank_name": "CB KUBAN KREDIT LLC",
            "country_name": "RUSSIAN FEDERATION",
            "country_img": "https://bincheck.io/assets/flags/svg/ru.svg",
            "country_url": "https://bincheck.io/es/ru",
            "bank_url": "https://bincheck.io/es/ru/cb-kuban-kredit-llc"
        },
        {
            "bin_num": "416740",
            "bin_mark": "VISA",
            "bin_type": "DEBIT",
            "bin_level": "CLASSIC",
            "bank_name": "CB KUBAN KREDIT LLC",
            "country_name": "RUSSIAN FEDERATION",
            "country_img": "https://bincheck.io/assets/flags/svg/ru.svg",
            "country_url": "https://bincheck.io/es/ru",
            "bank_url": "https://bincheck.io/es/ru/cb-kuban-kredit-llc"
        },
        {
            "bin_num": "416741",
            "bin_mark": "VISA",
            "bin_type": "DEBIT",
            "bin_level": "GOLD",
            "bank_name": "CB KUBAN KREDIT LLC",
            "country_name": "RUSSIAN FEDERATION",
            "country_img": "https://bincheck.io/assets/flags/svg/ru.svg",
            "country_url": "https://bincheck.io/es/ru",
            "bank_url": "https://bincheck.io/es/ru/cb-kuban-kredit-llc"
        },
        {
            "bin_num": "416742",
            "bin_mark": "VISA",
            "bin_type": "DEBIT",
            "bin_level": "BUSINESS",
            "bank_name": "CB KUBAN KREDIT LLC",
            "country_name": "RUSSIAN FEDERATION",
            "country_img": "https://bincheck.io/assets/flags/svg/ru.svg",
            "country_url": "https://bincheck.io/es/ru",
            "bank_url": "https://bincheck.io/es/ru/cb-kuban-kredit-llc"
        },
        {
            "bin_num": "416743",
            "bin_mark": "VISA",
            "bin_type": "DEBIT",
            "bin_level": "ELECTRON",
            "bank_name": "CB KUBAN KREDIT LLC",
            "country_name": "RUSSIAN FEDERATION",
            "country_img": "https://bincheck.io/assets/flags/svg/ru.svg",
            "country_url": "https://bincheck.io/es/ru",
            "bank_url": "https://bincheck.io/es/ru/cb-kuban-kredit-llc"
        },
        {
            "bin_num": "428176",
            "bin_mark": "VISA",
            "bin_type": "DEBIT",
            "bin_level": "ELECTRON",
            "bank_name": "CB KUBAN KREDIT LLC",
            "country_name": "RUSSIAN FEDERATION",
            "country_img": "https://bincheck.io/assets/flags/svg/ru.svg",
            "country_url": "https://bincheck.io/es/ru",
            "bank_url": "https://bincheck.io/es/ru/cb-kuban-kredit-llc"
        },
        {
            "bin_num": "446901",
            "bin_mark": "VISA",
            "bin_type": "DEBIT",
            "bin_level": "INFINITE",
            "bank_name": "CB KUBAN KREDIT LLC",
            "country_name": "RUSSIAN FEDERATION",
            "country_img": "https://bincheck.io/assets/flags/svg/ru.svg",
            "country_url": "https://bincheck.io/es/ru",
            "bank_url": "https://bincheck.io/es/ru/cb-kuban-kredit-llc"
        },
        {
            "bin_num": "557976",
            "bin_mark": "MASTERCARD",
            "bin_type": "DEBIT",
            "bin_level": "STANDARD",
            "bank_name": "CB KUBAN KREDIT LLC",
            "country_name": "RUSSIAN FEDERATION",
            "country_img": "https://bincheck.io/assets/flags/svg/ru.svg",
            "country_url": "https://bincheck.io/es/ru",
            "bank_url": "https://bincheck.io/es/ru/cb-kuban-kredit-llc"
        }
    ]
}