{
    "data": [
        {
            "bin_num": "512552",
            "bin_mark": "MASTERCARD",
            "bin_type": "CREDIT",
            "bin_level": "STANDARD",
            "bank_name": "EUROPAY 6000",
            "country_name": "SPAIN",
            "country_img": "https://bincheck.io/assets/flags/svg/es.svg",
            "country_url": "https://bincheck.io/es/esp",
            "bank_url": "https://bincheck.io/es/esp/europay-6000"
        },
        {
            "bin_num": "512584",
            "bin_mark": "MASTERCARD",
            "bin_type": "CREDIT",
            "bin_level": "",
            "bank_name": "EUROPAY 6000",
            "country_name": "SPAIN",
            "country_img": "https://bincheck.io/assets/flags/svg/es.svg",
            "country_url": "https://bincheck.io/es/esp",
            "bank_url": "https://bincheck.io/es/esp/europay-6000"
        },
        {
            "bin_num": "554037",
            "bin_mark": "MASTERCARD",
            "bin_type": "CREDIT",
            "bin_level": "PERSONAL",
            "bank_name": "EUROPAY 6000",
            "country_name": "SPAIN",
            "country_img": "https://bincheck.io/assets/flags/svg/es.svg",
            "country_url": "https://bincheck.io/es/esp",
            "bank_url": "https://bincheck.io/es/esp/europay-6000"
        },
        {
            "bin_num": "554039",
            "bin_mark": "MASTERCARD",
            "bin_type": "CREDIT",
            "bin_level": "",
            "bank_name": "EUROPAY 6000",
            "country_name": "SPAIN",
            "country_img": "https://bincheck.io/assets/flags/svg/es.svg",
            "country_url": "https://bincheck.io/es/esp",
            "bank_url": "https://bincheck.io/es/esp/europay-6000"
        },
        {
            "bin_num": "554060",
            "bin_mark": "MASTERCARD",
            "bin_type": "CREDIT",
            "bin_level": "STANDARD",
            "bank_name": "EUROPAY 6000",
            "country_name": "SPAIN",
            "country_img": "https://bincheck.io/assets/flags/svg/es.svg",
            "country_url": "https://bincheck.io/es/esp",
            "bank_url": "https://bincheck.io/es/esp/europay-6000"
        },
        {
            "bin_num": "558541",
            "bin_mark": "MASTERCARD",
            "bin_type": "CREDIT",
            "bin_level": "",
            "bank_name": "EUROPAY 6000",
            "country_name": "SPAIN",
            "country_img": "https://bincheck.io/assets/flags/svg/es.svg",
            "country_url": "https://bincheck.io/es/esp",
            "bank_url": "https://bincheck.io/es/esp/europay-6000"
        },
        {
            "bin_num": "558571",
            "bin_mark": "MASTERCARD",
            "bin_type": "CREDIT",
            "bin_level": "BUSINESS",
            "bank_name": "EUROPAY 6000",
            "country_name": "SPAIN",
            "country_img": "https://bincheck.io/assets/flags/svg/es.svg",
            "country_url": "https://bincheck.io/es/esp",
            "bank_url": "https://bincheck.io/es/esp/europay-6000"
        }
    ]
}