{
    "data": [
        {
            "bin_num": "372290",
            "bin_mark": "AMERICAN",
            "bin_type": "CREDIT",
            "bin_level": "PERSONAL GREEN CHARGE",
            "bank_name": "SWISSCARD (REVOLVE PORTFOLIO)",
            "country_name": "SWITZERLAND",
            "country_img": "https://bincheck.io/assets/flags/svg/ch.svg",
            "country_url": "https://bincheck.io/es/ch",
            "bank_url": "https://bincheck.io/es/ch/swisscard-(revolve-portfolio)"
        },
        {
            "bin_num": "377660",
            "bin_mark": "AMERICAN",
            "bin_type": "CREDIT",
            "bin_level": "OPEN GOLD REVOLVE",
            "bank_name": "SWISSCARD (REVOLVE PORTFOLIO)",
            "country_name": "SWITZERLAND",
            "country_img": "https://bincheck.io/assets/flags/svg/ch.svg",
            "country_url": "https://bincheck.io/es/ch",
            "bank_url": "https://bincheck.io/es/ch/swisscard-(revolve-portfolio)"
        },
        {
            "bin_num": "377661",
            "bin_mark": "AMERICAN",
            "bin_type": "CREDIT",
            "bin_level": "OPEN GOLD REVOLVE",
            "bank_name": "SWISSCARD (REVOLVE PORTFOLIO)",
            "country_name": "SWITZERLAND",
            "country_img": "https://bincheck.io/assets/flags/svg/ch.svg",
            "country_url": "https://bincheck.io/es/ch",
            "bank_url": "https://bincheck.io/es/ch/swisscard-(revolve-portfolio)"
        },
        {
            "bin_num": "377662",
            "bin_mark": "AMERICAN",
            "bin_type": "CREDIT",
            "bin_level": "PERSONAL PLATINUM CHARGE",
            "bank_name": "SWISSCARD (REVOLVE PORTFOLIO)",
            "country_name": "SWITZERLAND",
            "country_img": "https://bincheck.io/assets/flags/svg/ch.svg",
            "country_url": "https://bincheck.io/es/ch",
            "bank_url": "https://bincheck.io/es/ch/swisscard-(revolve-portfolio)"
        },
        {
            "bin_num": "377673",
            "bin_mark": "AMERICAN",
            "bin_type": "CREDIT",
            "bin_level": "PERSONAL GREEN CHARGE",
            "bank_name": "SWISSCARD (REVOLVE PORTFOLIO)",
            "country_name": "SWITZERLAND",
            "country_img": "https://bincheck.io/assets/flags/svg/ch.svg",
            "country_url": "https://bincheck.io/es/ch",
            "bank_url": "https://bincheck.io/es/ch/swisscard-(revolve-portfolio)"
        }
    ]
}