{
    "data": [
        {
            "bin_num": "514738",
            "bin_mark": "MASTERCARD",
            "bin_type": "CREDIT",
            "bin_level": "WORLD",
            "bank_name": "SHANGHAI COMMERCIAL & SAVINGS BANK, LTD., THE",
            "country_name": "TAIWAN, PROVINCE OF CHINA",
            "country_img": "https://bincheck.io/assets/flags/svg/tw.svg",
            "country_url": "https://bincheck.io/es/tw",
            "bank_url": "https://bincheck.io/es/tw/shanghai-commercial-&-savings-bank,-ltd.,-the"
        },
        {
            "bin_num": "515699",
            "bin_mark": "MASTERCARD",
            "bin_type": "CREDIT",
            "bin_level": "EXECUTIVE",
            "bank_name": "SHANGHAI COMMERCIAL & SAVINGS BANK, LTD., THE",
            "country_name": "TAIWAN, PROVINCE OF CHINA",
            "country_img": "https://bincheck.io/assets/flags/svg/tw.svg",
            "country_url": "https://bincheck.io/es/tw",
            "bank_url": "https://bincheck.io/es/tw/shanghai-commercial-&-savings-bank,-ltd.,-the"
        },
        {
            "bin_num": "522232",
            "bin_mark": "MASTERCARD",
            "bin_type": "CREDIT",
            "bin_level": "TITANIUM",
            "bank_name": "SHANGHAI COMMERCIAL & SAVINGS BANK, LTD., THE",
            "country_name": "TAIWAN, PROVINCE OF CHINA",
            "country_img": "https://bincheck.io/assets/flags/svg/tw.svg",
            "country_url": "https://bincheck.io/es/tw",
            "bank_url": "https://bincheck.io/es/tw/shanghai-commercial-&-savings-bank,-ltd.,-the"
        },
        {
            "bin_num": "524117",
            "bin_mark": "MASTERCARD",
            "bin_type": "CREDIT",
            "bin_level": "TITANIUM",
            "bank_name": "SHANGHAI COMMERCIAL & SAVINGS BANK, LTD., THE",
            "country_name": "TAIWAN, PROVINCE OF CHINA",
            "country_img": "https://bincheck.io/assets/flags/svg/tw.svg",
            "country_url": "https://bincheck.io/es/tw",
            "bank_url": "https://bincheck.io/es/tw/shanghai-commercial-&-savings-bank,-ltd.,-the"
        },
        {
            "bin_num": "540853",
            "bin_mark": "MASTERCARD",
            "bin_type": "CREDIT",
            "bin_level": "GOLD",
            "bank_name": "SHANGHAI COMMERCIAL & SAVINGS BANK, LTD., THE",
            "country_name": "TAIWAN, PROVINCE OF CHINA",
            "country_img": "https://bincheck.io/assets/flags/svg/tw.svg",
            "country_url": "https://bincheck.io/es/tw",
            "bank_url": "https://bincheck.io/es/tw/shanghai-commercial-&-savings-bank,-ltd.,-the"
        },
        {
            "bin_num": "543373",
            "bin_mark": "MASTERCARD",
            "bin_type": "CREDIT",
            "bin_level": "STANDARD",
            "bank_name": "SHANGHAI COMMERCIAL & SAVINGS BANK, LTD., THE",
            "country_name": "TAIWAN, PROVINCE OF CHINA",
            "country_img": "https://bincheck.io/assets/flags/svg/tw.svg",
            "country_url": "https://bincheck.io/es/tw",
            "bank_url": "https://bincheck.io/es/tw/shanghai-commercial-&-savings-bank,-ltd.,-the"
        }
    ]
}